partiqle/__init__.py
partiqle-0.0.0.dist-info/LICENSE
partiqle-0.0.0.dist-info/WHEEL
partiqle-0.0.0.dist-info/METADATA
partiqle-0.0.0.dist-info/RECORD
