Metadata-Version: 2.1
Name: partiqle
Version: 0.0.0
Summary: DynamoDB PartiQL support for Python
License: MIT
Author: Seonghyeon Kim
Author-email: self@seonghyeon.dev
Requires-Python: >=3.7,<4.0
Classifier: License :: OSI Approved :: MIT License
Classifier: Programming Language :: Python :: 3
Classifier: Programming Language :: Python :: 3.7
Classifier: Programming Language :: Python :: 3.8
Classifier: Programming Language :: Python :: 3.9
Requires-Dist: boto3 (>=1.17.53,<2.0.0)
